{
  "capitulo_codigo": "01",
  "partidas": [
    {
      "codigo": "m23E02AM010",
      "subcapitulo_codigo": "01.03",
      "unidad": "m2",
      "cantidad": 332.0,
      "precio": 1.03,
      "importe": 341.96
    },
    {
      "codigo": "m23E02AM020",
      "subcapitulo_codigo": "01.03",
      "unidad": "m2",
      "cantidad": 332.0,
      "precio": 1.55,
      "importe": 514.60
    },
    {
      "codigo": "m23E02CM020",
      "subcapitulo_codigo": "01.03",
      "unidad": "m3",
      "cantidad": 274.55,
      "precio": 4.55,
      "importe": 1249.20
    },
    {
      "codigo": "m23E02CM030",
      "subcapitulo_codigo": "01.03",
      "unidad": "m3",
      "cantidad": 150.0,
      "precio": 5.25,
      "importe": 787.50
    },
    {
      "codigo": "m23E02SA060",
      "subcapitulo_codigo": "01.03",
      "unidad": "m3",
      "cantidad": 274.55,
      "precio": 5.81,
      "importe": 1595.14
    },
    {
      "codigo": "APUDm23U02H050n3",
      "subcapitulo_codigo": "01.03",
      "unidad": "m3",
      "cantidad": 274.5,
      "precio": 2.66,
      "importe": 730.17
    }
  ],
  "total_extraido": 5858.57,
  "num_partidas": 6
}