{
  "capitulo_codigo": "02",
  "partidas": [
    {
      "codigo": "m23U13DQA200",
      "unidad": "ud",
      "cantidad": 14.00,
      "precio": 441.65,
      "importe": 6183.10
    },
    {
      "codigo": "APUDV_BAM37.D3u.d08",
      "unidad": "ud",
      "cantidad": 24.00,
      "precio": 647.84,
      "importe": 15548.16
    },
    {
      "codigo": "m23U13C010",
      "unidad": "ud",
      "cantidad": 14.00,
      "precio": 38.54,
      "importe": 539.56
    },
    {
      "codigo": "m23U13AS020",
      "unidad": "ud",
      "cantidad": 28.00,
      "precio": 14.80,
      "importe": 414.40
    },
    {
      "codigo": "m23E27HA030",
      "unidad": "m2",
      "cantidad": 1.00,
      "precio": 6.50,
      "importe": 6.50
    },
    {
      "codigo": "m23E27HE010",
      "unidad": "m2",
      "cantidad": 1.00,
      "precio": 17.77,
      "importe": 17.77
    },
    {
      "codigo": "m23U13DR070",
      "unidad": "ud",
      "cantidad": 1.00,
      "precio": 44.88,
      "importe": 44.88
    },
    {
      "codigo": "m23U13DR080",
      "unidad": "ud",
      "cantidad": 1.00,
      "precio": 63.63,
      "importe": 63.63
    },
    {
      "codigo": "m23U13DR100",
      "unidad": "ud",
      "cantidad": 1.00,
      "precio": 85.67,
      "importe": 85.67
    },
    {
      "codigo": "APUI_005",
      "unidad": "d",
      "cantidad": 2.00,
      "precio": 974.03,
      "importe": 1948.06
    }
  ]
}